{
  "length": {
    "length": 4
  },
  "tasks": [
    {
      "description": "2 + 2 = 4 = 4\n",
      "tags": [
        "fefefe"
      ],
      "order": 5,
      "last_modified": "2021-11-05T22:37:18.358Z",
      "time_added": "2021-10-20T10:54:54.415Z",
      "id": 27
    },
    {
      "description": "1 2 3 4 5555 5 5",
      "tags": [
        "yeet"
      ],
      "order": 3,
      "last_modified": "2021-11-05T22:34:01.344Z",
      "time_added": "2021-11-02T17:42:15.332Z",
      "id": 30
    },
    {
      "description": "look alive look alive",
      "tags": [
        "yyyyy",
        "buggin"
      ],
      "order": 6,
      "last_modified": "2021-11-05T22:31:34.796Z",
      "time_added": "2021-10-19T14:17:52.080Z",
      "id": 31
    },
    {
      "description": "keep it open",
      "tags": [
        "tt",
        "adding",
        "more",
        "and more",
        "tags",
        "till this",
        "scrolls",
        "one"
      ],
      "order": 2,
      "last_modified": "2021-11-03T22:59:28.082Z",
      "time_added": "2021-11-03T21:10:22.431Z",
      "id": 32
    },
    {
      "description": "1 2 3 4 5555 5 wacka wacka\n",
      "tags": [
        "yeet"
      ],
      "order": 4,
      "last_modified": "2021-11-05T22:33:57.701Z",
      "time_added": "2021-11-02T17:42:15.332Z",
      "id": 33
    },
    {
      "description": "why are they all emptying idk",
      "tags": [
        "aaa",
        "wacka"
      ],
      "order": 1,
      "last_modified": "2021-11-03T22:59:41.987Z",
      "time_added": "2021-10-20T10:22:26.548Z",
      "id": 34
    }
  ],
  "completed": [
    {
      "description": "order testing",
      "tags": [
        "order",
        "anotha"
      ],
      "order": 2,
      "last_modified": "2021-11-05T22:43:02.691Z",
      "time_added": "2021-10-20T10:08:36.709Z",
      "id": 38
    },
    {
      "description": "sds\n",
      "tags": [
        "aaa",
        "wacka",
        "p2"
      ],
      "order": 1,
      "last_modified": "2021-11-05T22:43:14.101Z",
      "time_added": "2021-10-20T10:44:33.562Z",
      "id": 48
    },
    {
      "description": "eewewe fill me again diwdiwdmwd austin is",
      "tags": [
        "aaa",
        "adding",
        "and more",
        "austin",
        "buggin",
        "d",
        "fefefe",
        "ffeefe",
        "lalier",
        "laziest",
        "lazy",
        "more",
        "one",
        "scrolls",
        "steezy",
        "tag me",
        "tags",
        "till this",
        "tt",
        "uff",
        "wacka",
        "yeet",
        "yyyyy"
      ],
      "order": 3,
      "last_modified": "2021-11-05T22:43:09.738Z",
      "time_added": "2021-10-19T14:17:34.859Z",
      "id": 49
    }
  ]
}